nbquiz/__init__.py
nbquiz-0.0.1.dist-info/LICENSE
nbquiz-0.0.1.dist-info/METADATA
nbquiz-0.0.1.dist-info/WHEEL
nbquiz-0.0.1.dist-info/top_level.txt
nbquiz-0.0.1.dist-info/RECORD
