Metadata-Version: 2.1
Name: nbquiz
Version: 0.0.1
Summary: Make ipywidgets-based quizzes for use in Jupyter notebooks
Author-email: "J. Ellerbroek" <j.ellerbroek@tudelft.nl>
Maintainer-email: "J. Ellerbroek" <j.ellerbroek@tudelft.nl>
License: MIT License
Project-URL: Homepage, https://github.com/TUDelft-AE-Python/nbquiz
Project-URL: Bug Reports, https://github.com/TUDelft-AE-Python/nbquiz/issues
Project-URL: Source, https://github.com/TUDelft-AE-Python/nbquiz
Keywords: education,quiz,jupyter,notebook
Classifier: Development Status :: 3 - Alpha
Classifier: License :: OSI Approved :: MIT License
Classifier: Programming Language :: Python :: 3
Classifier: Programming Language :: Python :: 3.8
Classifier: Programming Language :: Python :: 3.9
Classifier: Programming Language :: Python :: 3.10
Classifier: Programming Language :: Python :: 3.11
Classifier: Programming Language :: Python :: 3.12
Classifier: Programming Language :: Python :: 3 :: Only
Requires-Python: >=3.8
License-File: LICENSE
Requires-Dist: ipywidgets
Requires-Dist: ipython
